hdrstats/__init__.py
hdrstats/cli.py
hdrstats/hdrstats.py
hdrstats/humanblur.csh
hdrstats/humanblur_nh.csh
hdrstats/image.py
hdrstats-0.1.10.data/data/bin/humanblur.csh
hdrstats-0.1.10.data/data/bin/humanblur_nh.csh
hdrstats-0.1.10.dist-info/LICENSE
hdrstats-0.1.10.dist-info/METADATA
hdrstats-0.1.10.dist-info/WHEEL
hdrstats-0.1.10.dist-info/entry_points.txt
hdrstats-0.1.10.dist-info/top_level.txt
hdrstats-0.1.10.dist-info/zip-safe
hdrstats-0.1.10.dist-info/RECORD
