Metadata-Version: 2.1
Name: hdrstats
Version: 0.1.10
Summary: image base calculations and statistical analysis
Home-page: https://bitbucket.org/stephenwasilewski/hdrstats
Author: Stephen Wasilewski
Author-email: stephanwaz@gmail.com
License: Mozilla Public License 2.0 (MPL 2.0)
Keywords: hdrstats
Platform: UNKNOWN
Classifier: Development Status :: 2 - Pre-Alpha
Classifier: License :: OSI Approved :: Mozilla Public License 2.0 (MPL 2.0)
Classifier: Natural Language :: English
Classifier: Programming Language :: Python :: 3.6
Classifier: Programming Language :: Python :: 3.7
Requires-Python: >=3.6
Requires-Dist: clasp
Requires-Dist: scipy
Requires-Dist: numpy
Requires-Dist: sklearn
